season/__init__.py
season/cmd.py
season/version.py
season/command/bundle.py
season/command/create.py
season/command/daemon.py
season/command/ide.py
season/command/service.py
season/command/__pycache__/bundle.cpython-314.pyc
season/command/__pycache__/create.cpython-314.pyc
season/command/__pycache__/daemon.cpython-314.pyc
season/command/__pycache__/ide.cpython-314.pyc
season/command/__pycache__/service.cpython-314.pyc
season/data/ide/package.json
season/data/ide/angular/angular.build.options.json
season/data/ide/angular/index.html
season/data/ide/angular/index.pug
season/data/ide/angular/main.ts
season/data/ide/angular/package.json
season/data/ide/angular/wiz.ts
season/data/ide/angular/wizbuild.js
season/data/ide/angular/app/app.component.html
season/data/ide/angular/app/app.component.pug
season/data/ide/angular/app/app.component.scss
season/data/ide/angular/app/app.component.ts
season/data/ide/angular/app/app.module.ts
season/data/ide/angular/libs/plugin.json
season/data/ide/angular/libs/ngx-loading/.browserslistrc
season/data/ide/angular/libs/ngx-loading/.eslintrc.json
season/data/ide/angular/libs/ngx-loading/LICENSE
season/data/ide/angular/libs/ngx-loading/README.md
season/data/ide/angular/libs/ngx-loading/karma.conf.js
season/data/ide/angular/libs/ngx-loading/ng-package.json
season/data/ide/angular/libs/ngx-loading/package.json
season/data/ide/angular/libs/ngx-loading/tsconfig.lib.json
season/data/ide/angular/libs/ngx-loading/tsconfig.lib.prod.json
season/data/ide/angular/libs/ngx-loading/tsconfig.spec.json
season/data/ide/angular/libs/ngx-loading/src/public-api.ts
season/data/ide/angular/libs/ngx-loading/src/test.ts
season/data/ide/angular/libs/ngx-loading/src/lib/ngx-loading-config.ts
season/data/ide/angular/libs/ngx-loading/src/lib/ngx-loading.component.spec.ts
season/data/ide/angular/libs/ngx-loading/src/lib/ngx-loading.component.ts
season/data/ide/angular/libs/ngx-loading/src/lib/ngx-loading.module.ts
season-2.4.15.dist-info/licenses/LICENSE
season-2.4.15.dist-info/METADATA
season-2.4.15.dist-info/WHEEL
season-2.4.15.dist-info/entry_points.txt
season-2.4.15.dist-info/top_level.txt
season-2.4.15.dist-info/RECORD
