Metadata-Version: 2.4
Name: season
Version: 2.4.15
Summary: season wiz web framework
Home-page: https://github.com/season-framework/wiz
Author: proin
Author-email: proin@season.co.kr
License: MIT
Classifier: License :: OSI Approved :: MIT License
Requires-Python: >=3.8
License-File: LICENSE
Requires-Dist: werkzeug==3.0.1
Requires-Dist: jinja2==3.1.3
Requires-Dist: texttable
Requires-Dist: flask==3.0.2
Requires-Dist: python-socketio==5.11.1
Requires-Dist: flask-socketio==5.3.6
Requires-Dist: langchain
Requires-Dist: langchain-community
Requires-Dist: langchain-openai
Requires-Dist: rank_bm25
Requires-Dist: unstructured
Requires-Dist: python-pptx
Requires-Dist: openpyxl
Requires-Dist: argh
Requires-Dist: psutil
Requires-Dist: GitPython
Requires-Dist: numpy
Requires-Dist: pandas
Requires-Dist: Pillow
Requires-Dist: requests
Requires-Dist: eventlet
Requires-Dist: gevent
Requires-Dist: natsort
Dynamic: author
Dynamic: author-email
Dynamic: classifier
Dynamic: description
Dynamic: description-content-type
Dynamic: home-page
Dynamic: license
Dynamic: license-file
Dynamic: requires-dist
Dynamic: requires-python
Dynamic: summary
